stashpr.py
stash_pull_request-1.2.0.dist-info/DESCRIPTION.rst
stash_pull_request-1.2.0.dist-info/METADATA
stash_pull_request-1.2.0.dist-info/RECORD
stash_pull_request-1.2.0.dist-info/WHEEL
stash_pull_request-1.2.0.dist-info/entry_points.txt
stash_pull_request-1.2.0.dist-info/metadata.json
stash_pull_request-1.2.0.dist-info/pbr.json
stash_pull_request-1.2.0.dist-info/top_level.txt
