Metadata-Version: 2.0
Name: stash-pull-request
Version: 1.2.0
Summary: send pull request on stash
Home-page: UNKNOWN
Author: David Keijser
Author-email: keijser@gmail.com
License: MIT
Platform: UNKNOWN
Requires-Dist: autoauth
Requires-Dist: requests (>=1.1)
